maryam_dvalishvili/__init__.py
maryam_dvalishvili/hbd.py
maryam_dvalishvili-0.1.dist-info/METADATA
maryam_dvalishvili-0.1.dist-info/WHEEL
maryam_dvalishvili-0.1.dist-info/top_level.txt
maryam_dvalishvili-0.1.dist-info/RECORD
