Metadata-Version: 2.1
Name: maryam-dvalishvili
Version: 0.1
Summary: My Python package for birthday greetings
Home-page: UNKNOWN
Author: a_bitsadze
Author-email: alika.bitsadze@gmail.com
License: UNKNOWN
Platform: UNKNOWN
